{
    "filename": "images/20/000237.jpg",
    "height": 1024,
    "width": 1024,
    "annots": [
        {
            "personID": 0,
            "bbox": [118.80, 225.80, 510.98, 843.00, 0.81],
            "bbox_handl2d": [345.78, 457.86, 399.02, 493.49, 0.64],
            "bbox_handr2d": [179.96, 294.31, 220.61, 331.26, 0.31],
            "keypoints": [
              [ 386.13,  296.70,    0.88], 
              [ 433.61,  344.17,    0.90], 
              [ 389.09,  341.54,    0.89], 
              [ 305.12,  369.42,    0.90], 
              [ 232.34,  327.61,    0.86], 
              [ 472.91,  344.25,    0.84], 
              [ 478.30,  439.32,    0.88], 
              [ 408.52,  467.31,    0.83], 
              [ 414.08,  503.64,    0.78], 
              [ 389.00,  495.23,    0.75], 
              [ 282.91,  548.44,    0.86], 
              [ 213.04,  679.80,    0.84], 
              [ 436.52,  517.58,    0.71], 
              [ 416.97,  657.41,    0.89], 
              [ 455.95,  769.14,    0.90], 
              [ 377.85,  279.96,    0.35], 
              [ 391.78,  280.00,    0.96], 
              [   0.00,    0.00,    0.00], 
              [ 433.75,  277.23,    0.93], 
              [ 400.17,  788.60,    0.78], 
              [ 414.17,  791.57,    0.88], 
              [ 464.50,  774.78,    0.81], 
              [ 151.49,  679.58,    0.72], 
              [ 162.61,  674.06,    0.68], 
              [ 224.15,  702.00,    0.69]
            ],
            "handl2d": [
              [ 394.58,  472.36,    0.59], 
              [ 381.31,  468.51,    0.38], 
              [ 364.19,  467.12,    0.39], 
              [ 355.81,  472.36,    0.65], 
              [ 350.22,  480.74,    0.80], 
              [ 372.92,  460.83,    0.86], 
              [ 361.74,  469.21,    0.63], 
              [ 356.50,  474.45,    0.36], 
              [ 362.79,  474.80,    0.27], 
              [ 379.56,  466.76,    0.76], 
              [ 365.24,  481.79,    0.81], 
              [ 368.03,  481.44,    0.59], 
              [ 371.53,  478.29,    0.67], 
              [ 385.85,  474.10,    0.72], 
              [ 372.57,  487.03,    0.82], 
              [ 374.32,  485.98,    0.65], 
              [ 377.12,  483.19,    0.64], 
              [ 390.04,  481.44,    0.73], 
              [ 379.21,  490.52,    0.73], 
              [ 380.26,  489.47,    0.74], 
              [ 382.01,  488.43,    0.64]
            ],
            "handr2d": [
              [ 209.69,  317.91,    0.04], 
              [ 217.22,  313.47,    0.07], 
              [ 210.72,  301.83,    0.03], 
              [ 203.88,  299.10,    0.06], 
              [ 199.77,  297.39,    0.07], 
              [ 215.85,  312.44,    0.15], 
              [ 206.61,  303.89,    0.29], 
              [ 198.75,  301.83,    0.37], 
              [ 192.59,  301.49,    0.50], 
              [ 212.09,  318.60,    0.21], 
              [ 200.46,  312.44,    0.27], 
              [ 192.59,  310.05,    0.35], 
              [ 185.40,  311.75,    0.35], 
              [ 206.61,  324.07,    0.28], 
              [ 197.38,  320.31,    0.29], 
              [ 188.14,  316.89,    0.47], 
              [ 183.35,  314.83,    0.46], 
              [ 202.17,  328.18,    0.27], 
              [ 192.25,  326.47,    0.43], 
              [ 187.46,  323.39,    0.55], 
              [ 183.69,  320.31,    0.41]
            ],
            "isKeyframe": false
        }
    ],
    "isKeyframe": false
}

