{
    "filename": "images/16/000005.jpg",
    "height": 1024,
    "width": 1024,
    "annots": [
        {
            "personID": 0,
            "bbox": [373.11, 172.66, 732.07, 823.42, 0.78],
            "bbox_handl2d": [0.00, 0.00, 100.00, 100.00, 0.00],
            "bbox_handr2d": [639.18, 191.73, 679.29, 228.11, 0.41],
            "keypoints": [
              [   0.00,    0.00,    0.00], 
              [ 548.38,  308.03,    0.87], 
              [ 612.52,  322.06,    0.87], 
              [ 702.15,  293.97,    0.88], 
              [ 671.31,  226.89,    0.80], 
              [ 495.26,  299.65,    0.88], 
              [ 433.66,  372.29,    0.90], 
              [ 489.68,  386.13,    0.56], 
              [ 497.93,  495.24,    0.73], 
              [ 526.10,  503.67,    0.73], 
              [ 534.37,  629.44,    0.81], 
              [ 526.12,  752.35,    0.85], 
              [ 458.89,  481.33,    0.75], 
              [ 436.53,  568.00,    0.89], 
              [ 414.12,  685.25,    0.85], 
              [   0.00,    0.00,    0.00], 
              [   0.00,    0.00,    0.00], 
              [ 612.62,  238.14,    0.89], 
              [ 545.54,  226.90,    0.86], 
              [ 414.29,  702.07,    0.47], 
              [ 403.02,  702.04,    0.55], 
              [ 411.46,  702.15,    0.85], 
              [ 539.98,  744.02,    0.64], 
              [ 548.23,  749.53,    0.72], 
              [ 523.28,  769.19,    0.86]
            ],
            "handl2d": [
              [ 498.38,  383.00,    0.01], 
              [ 496.98,  390.69,    0.01], 
              [ 498.73,  385.80,    0.01], 
              [ 499.08,  385.80,    0.01], 
              [ 502.23,  390.34,    0.01], 
              [ 501.18,  385.10,    0.01], 
              [ 507.46,  378.81,    0.01], 
              [ 510.26,  383.70,    0.01], 
              [ 510.61,  387.90,    0.00], 
              [ 499.43,  386.50,    0.01], 
              [ 506.42,  386.15,    0.01], 
              [ 506.07,  389.29,    0.01], 
              [ 501.88,  394.19,    0.00], 
              [ 499.43,  387.55,    0.01], 
              [ 499.78,  387.20,    0.01], 
              [ 501.88,  390.34,    0.01], 
              [ 502.23,  392.79,    0.00], 
              [ 499.43,  388.25,    0.01], 
              [ 500.13,  387.90,    0.01], 
              [ 501.88,  389.29,    0.01], 
              [ 504.67,  391.74,    0.00]
            ],
            "handr2d": [
              [ 671.12,  225.08,    0.40], 
              [ 659.75,  221.98,    0.51], 
              [ 648.03,  214.75,    0.48], 
              [ 642.87,  208.54,    0.67], 
              [ 642.52,  206.13,    0.63], 
              [ 653.89,  194.76,    0.63], 
              [ 648.72,  197.86,    0.33], 
              [ 648.38,  201.65,    0.32], 
              [ 647.34,  206.47,    0.24], 
              [ 662.51,  195.10,    0.56], 
              [ 656.65,  198.20,    0.35], 
              [ 653.89,  206.47,    0.34], 
              [ 654.24,  211.30,    0.31], 
              [ 670.09,  197.51,    0.63], 
              [ 662.51,  205.10,    0.30], 
              [ 661.13,  210.26,    0.28], 
              [ 660.78,  213.71,    0.26], 
              [ 675.95,  201.65,    0.58], 
              [ 670.43,  207.16,    0.26], 
              [ 668.37,  212.68,    0.24], 
              [ 668.02,  214.75,    0.24]
            ],
            "isKeyframe": false
        }
    ],
    "isKeyframe": false
}

