{
    "filename": "images/07/000391.jpg",
    "height": 1024,
    "width": 1024,
    "annots": [
        {
            "personID": 0,
            "bbox": [484.04, 256.22, 752.46, 809.72, 0.80],
            "bbox_handl2d": [709.59, 558.43, 748.33, 609.13, 0.38],
            "bbox_handr2d": [471.75, 396.43, 509.92, 428.12, 0.58],
            "keypoints": [
              [ 590.23,  319.03,    0.92], 
              [ 634.99,  361.01,    0.87], 
              [ 593.09,  338.68,    0.84], 
              [ 548.45,  369.39,    0.92], 
              [ 506.41,  394.72,    0.84], 
              [ 676.87,  383.35,    0.80], 
              [ 730.09,  461.68,    0.88], 
              [ 729.99,  559.48,    0.85], 
              [ 626.65,  517.58,    0.76], 
              [ 612.56,  509.19,    0.76], 
              [ 612.54,  612.64,    0.88], 
              [ 637.71,  688.08,    0.87], 
              [ 640.53,  523.15,    0.80], 
              [ 587.52,  615.52,    0.88], 
              [ 587.43,  746.80,    0.88], 
              [ 590.21,  302.34,    0.25], 
              [ 595.85,  302.49,    0.89], 
              [   0.00,    0.00,    0.00], 
              [ 637.67,  305.17,    0.94], 
              [ 542.71,  735.63,    0.79], 
              [ 545.60,  746.84,    0.89], 
              [ 593.13,  763.60,    0.78], 
              [ 609.82,  701.99,    0.56], 
              [ 612.59,  699.17,    0.56], 
              [ 648.99,  699.24,    0.75]
            ],
            "handl2d": [
              [ 728.76,  562.65,    0.48], 
              [ 719.59,  569.83,    0.54], 
              [ 712.82,  581.79,    0.50], 
              [ 715.21,  593.75,    0.50], 
              [ 719.59,  601.72,    0.56], 
              [ 719.59,  588.96,    0.55], 
              [ 723.58,  600.92,    0.37], 
              [ 725.97,  604.91,    0.21], 
              [ 724.77,  598.13,    0.18], 
              [ 728.76,  589.76,    0.52], 
              [ 731.55,  596.53,    0.36], 
              [ 733.94,  593.75,    0.21], 
              [ 734.34,  589.76,    0.19], 
              [ 737.53,  586.57,    0.46], 
              [ 739.52,  593.35,    0.39], 
              [ 738.73,  590.16,    0.31], 
              [ 736.73,  586.57,    0.25], 
              [ 743.51,  584.98,    0.42], 
              [ 745.11,  588.96,    0.34], 
              [ 743.91,  587.37,    0.33], 
              [ 742.31,  584.58,    0.30]
            ],
            "handr2d": [
              [ 500.94,  403.87,    0.12], 
              [ 504.14,  404.07,    0.39], 
              [ 506.74,  405.88,    0.56], 
              [ 502.14,  412.28,    0.73], 
              [ 497.33,  419.68,    0.69], 
              [ 487.13,  399.07,    0.72], 
              [ 490.53,  412.08,    0.73], 
              [ 494.73,  415.68,    0.57], 
              [ 496.74,  418.28,    0.45], 
              [ 480.73,  403.87,    0.75], 
              [ 486.73,  419.48,    0.78], 
              [ 491.53,  421.48,    0.65], 
              [ 492.73,  418.68,    0.48], 
              [ 477.13,  409.28,    0.62], 
              [ 483.13,  422.88,    0.72], 
              [ 488.33,  423.68,    0.58], 
              [ 489.73,  421.28,    0.44], 
              [ 474.93,  414.28,    0.55], 
              [ 479.13,  424.48,    0.71], 
              [ 483.53,  425.48,    0.56], 
              [ 485.53,  424.48,    0.41]
            ],
            "isKeyframe": false
        }
    ],
    "isKeyframe": false
}

