{
    "filename": "images/22/000107.jpg",
    "height": 1024,
    "width": 1024,
    "annots": [
        {
            "personID": 0,
            "bbox": [436.49, 212.98, 604.25, 816.59, 0.78],
            "bbox_handl2d": [580.27, 409.55, 616.84, 439.54, 0.54],
            "bbox_handr2d": [570.43, 248.53, 610.30, 278.96, 0.46],
            "keypoints": [
              [ 526.02,  277.31,    0.97], 
              [ 478.58,  327.54,    0.92], 
              [ 453.21,  327.59,    0.82], 
              [ 478.42,  347.04,    0.88], 
              [ 562.26,  280.14,    0.63], 
              [ 512.05,  333.07,    0.77], 
              [ 559.52,  369.39,    0.87], 
              [ 590.27,  408.55,    0.87], 
              [ 481.16,  495.27,    0.79], 
              [ 464.46,  500.72,    0.75], 
              [ 545.54,  623.81,    0.86], 
              [ 500.83,  749.50,    0.91], 
              [ 498.02,  489.69,    0.71], 
              [ 509.21,  576.26,    0.74], 
              [ 459.01,  660.18,    0.86], 
              [ 520.44,  263.28,    0.87], 
              [ 526.08,  268.76,    0.10], 
              [ 478.56,  268.87,    0.89], 
              [   0.00,    0.00,    0.00], 
              [ 495.19,  679.63,    0.59], 
              [ 492.39,  671.35,    0.54], 
              [ 450.47,  668.56,    0.78], 
              [ 551.12,  752.48,    0.84], 
              [ 542.74,  766.29,    0.84], 
              [ 481.39,  760.71,    0.83]
            ],
            "handl2d": [
              [ 592.74,  412.05,    0.19], 
              [ 587.92,  417.97,    0.35], 
              [ 583.31,  426.96,    0.73], 
              [ 589.01,  432.88,    0.61], 
              [ 596.47,  437.05,    0.79], 
              [ 593.84,  413.58,    0.65], 
              [ 596.47,  428.93,    0.79], 
              [ 594.93,  427.62,    0.47], 
              [ 594.06,  426.74,    0.24], 
              [ 601.07,  413.36,    0.67], 
              [ 602.39,  429.59,    0.72], 
              [ 600.42,  430.03,    0.54], 
              [ 599.76,  426.74,    0.36], 
              [ 606.77,  414.46,    0.72], 
              [ 608.31,  429.59,    0.71], 
              [ 606.55,  429.15,    0.47], 
              [ 605.68,  425.86,    0.26], 
              [ 612.26,  415.56,    0.76], 
              [ 613.79,  427.40,    0.52], 
              [ 613.35,  427.40,    0.52], 
              [ 612.04,  426.30,    0.32]
            ],
            "handr2d": [
              [ 573.75,  276.42,    0.67], 
              [ 574.62,  274.24,    0.45], 
              [ 586.43,  272.49,    0.34], 
              [ 598.67,  265.93,    0.19], 
              [ 599.11,  259.81,    0.25], 
              [ 588.17,  251.50,    0.52], 
              [ 599.98,  256.31,    0.27], 
              [ 604.35,  265.93,    0.28], 
              [ 598.67,  267.24,    0.31], 
              [ 590.36,  251.07,    0.66], 
              [ 604.79,  258.50,    0.36], 
              [ 602.60,  265.49,    0.38], 
              [ 596.04,  264.18,    0.29], 
              [ 592.98,  253.69,    0.62], 
              [ 606.54,  261.56,    0.57], 
              [ 602.60,  266.37,    0.47], 
              [ 597.79,  267.24,    0.52], 
              [ 595.17,  259.37,    0.58], 
              [ 606.97,  263.75,    0.68], 
              [ 603.91,  269.43,    0.65], 
              [ 598.67,  269.87,    0.67]
            ],
            "isKeyframe": false
        }
    ],
    "isKeyframe": false
}

