{
    "filename": "images/22/000143.jpg",
    "height": 1024,
    "width": 1024,
    "annots": [
        {
            "personID": 0,
            "bbox": [324.28, 120.35, 632.76, 761.13, 0.80],
            "bbox_handl2d": [0.00, 0.00, 100.00, 100.00, 0.00],
            "bbox_handr2d": [610.61, 415.86, 643.81, 437.02, 0.24],
            "keypoints": [
              [   0.00,    0.00,    0.00], 
              [ 444.91,  305.20,    0.85], 
              [ 495.26,  321.95,    0.86], 
              [ 539.98,  391.72,    0.90], 
              [ 607.05,  414.17,    0.88], 
              [ 394.62,  296.83,    0.85], 
              [ 349.99,  232.46,    0.89], 
              [ 389.07,  173.75,    0.84], 
              [ 456.03,  467.30,    0.79], 
              [ 481.35,  467.31,    0.75], 
              [ 542.80,  556.74,    0.84], 
              [ 526.10,  682.41,    0.88], 
              [ 422.59,  467.24,    0.71], 
              [ 439.32,  567.93,    0.87], 
              [ 447.70,  676.95,    0.85], 
              [   0.00,    0.00,    0.00], 
              [   0.00,    0.00,    0.00], 
              [ 478.53,  232.50,    0.92], 
              [ 425.38,  232.49,    0.63], 
              [ 478.50,  674.13,    0.64], 
              [ 472.86,  665.72,    0.52], 
              [ 442.15,  685.32,    0.80], 
              [ 567.85,  707.73,    0.76], 
              [ 553.98,  707.70,    0.76], 
              [ 520.35,  688.16,    0.80]
            ],
            "handl2d": [
              [ 393.63,  171.62,    0.02], 
              [ 391.33,  170.47,    0.02], 
              [ 388.17,  167.59,    0.01], 
              [ 392.19,  151.21,    0.01], 
              [ 413.75,  152.93,    0.01], 
              [ 393.63,  152.07,    0.02], 
              [ 392.48,  151.49,    0.02], 
              [ 412.89,  154.37,    0.02], 
              [ 414.90,  153.22,    0.01], 
              [ 401.39,  155.81,    0.02], 
              [ 402.83,  157.24,    0.02], 
              [ 410.30,  158.68,    0.02], 
              [ 414.62,  151.78,    0.01], 
              [ 403.69,  155.52,    0.02], 
              [ 411.74,  150.92,    0.02], 
              [ 412.89,  152.93,    0.02], 
              [ 412.89,  153.51,    0.01], 
              [ 391.62,  148.04,    0.03], 
              [ 416.34,  151.78,    0.02], 
              [ 415.48,  154.66,    0.03], 
              [ 415.77,  154.37,    0.02]
            ],
            "handr2d": [
              [ 613.38,  419.14,    0.15], 
              [ 617.33,  417.62,    0.35], 
              [ 627.36,  419.75,    0.48], 
              [ 634.96,  423.10,    0.55], 
              [ 641.04,  425.53,    0.67], 
              [ 624.93,  435.26,    0.42], 
              [ 631.32,  434.65,    0.25], 
              [ 636.79,  433.13,    0.43], 
              [ 640.74,  431.91,    0.44], 
              [ 624.63,  435.26,    0.19], 
              [ 630.71,  434.95,    0.08], 
              [ 632.84,  427.66,    0.13], 
              [ 634.96,  426.44,    0.14], 
              [ 624.02,  434.95,    0.12], 
              [ 630.40,  434.35,    0.06], 
              [ 632.53,  431.61,    0.09], 
              [ 633.75,  427.05,    0.10], 
              [ 620.98,  434.65,    0.08], 
              [ 631.32,  434.65,    0.06], 
              [ 633.75,  433.43,    0.08], 
              [ 633.75,  426.74,    0.06]
            ],
            "isKeyframe": false
        }
    ],
    "isKeyframe": false
}

