{
    "filename": "images/22/000302.jpg",
    "height": 1024,
    "width": 1024,
    "annots": [
        {
            "personID": 0,
            "bbox": [145.83, 201.69, 514.88, 738.44, 0.78],
            "bbox_handl2d": [281.31, 366.30, 334.53, 391.99, 0.60],
            "bbox_handr2d": [0.00, 0.00, 100.00, 100.00, 0.00],
            "keypoints": [
              [ 397.41,  257.82,    0.90], 
              [ 456.00,  302.38,    0.89], 
              [ 436.53,  302.36,    0.85], 
              [ 391.87,  319.13,    0.74], 
              [ 338.68,  319.17,    0.73], 
              [ 470.08,  302.44,    0.85], 
              [ 433.76,  369.62,    0.95], 
              [ 341.44,  386.27,    0.86], 
              [ 439.29,  456.12,    0.82], 
              [ 430.98,  455.99,    0.76], 
              [ 414.33,  576.28,    0.86], 
              [ 475.68,  668.53,    0.83], 
              [ 453.29,  458.82,    0.80], 
              [ 344.36,  492.48,    0.87], 
              [ 238.08,  601.48,    0.77], 
              [ 391.92,  252.11,    0.10], 
              [ 408.55,  252.10,    0.91], 
              [   0.00,    0.00,    0.00], 
              [ 439.29,  246.41,    0.88], 
              [ 176.58,  590.15,    0.71], 
              [ 187.87,  601.40,    0.74], 
              [ 235.37,  618.24,    0.64], 
              [ 428.18,  693.71,    0.74], 
              [ 433.74,  685.29,    0.75], 
              [ 484.13,  679.62,    0.84]
            ],
            "handl2d": [
              [ 330.10,  386.79,    0.58], 
              [ 318.63,  385.26,    0.45], 
              [ 305.63,  378.00,    0.29], 
              [ 291.48,  381.44,    0.45], 
              [ 285.74,  384.12,    0.84], 
              [ 303.33,  368.44,    0.77], 
              [ 291.86,  377.62,    0.50], 
              [ 291.86,  381.44,    0.49], 
              [ 297.60,  382.21,    0.36], 
              [ 306.39,  370.35,    0.70], 
              [ 293.01,  381.06,    0.54], 
              [ 297.21,  384.12,    0.63], 
              [ 301.04,  382.21,    0.60], 
              [ 309.07,  374.94,    0.81], 
              [ 296.45,  385.26,    0.59], 
              [ 301.04,  386.79,    0.57], 
              [ 304.48,  384.50,    0.59], 
              [ 310.21,  380.68,    0.78], 
              [ 299.89,  387.18,    0.62], 
              [ 303.33,  389.85,    0.68], 
              [ 307.54,  388.32,    0.72]
            ],
            "handr2d": [
              [ 335.43,  319.18,    0.02], 
              [ 320.47,  312.89,    0.02], 
              [ 312.67,  307.90,    0.04], 
              [ 313.10,  308.99,    0.02], 
              [ 309.42,  318.96,    0.02], 
              [ 314.19,  310.94,    0.03], 
              [ 311.58,  310.94,    0.03], 
              [ 308.11,  315.71,    0.05], 
              [ 308.11,  322.43,    0.03], 
              [ 313.10,  318.31,    0.03], 
              [ 311.37,  322.21,    0.04], 
              [ 310.72,  324.38,    0.05], 
              [ 309.63,  324.60,    0.03], 
              [ 316.35,  319.83,    0.02], 
              [ 310.28,  323.08,    0.03], 
              [ 311.58,  323.95,    0.03], 
              [ 310.72,  325.25,    0.02], 
              [ 313.75,  310.94,    0.03], 
              [ 311.58,  309.21,    0.02], 
              [ 314.19,  330.45,    0.02], 
              [ 314.62,  330.24,    0.01]
            ],
            "isKeyframe": false
        }
    ],
    "isKeyframe": false
}

