{
    "filename": "images/06/000127.jpg",
    "height": 1024,
    "width": 1024,
    "annots": [
        {
            "personID": 0,
            "bbox": [316.24, 253.76, 618.23, 837.25, 0.84],
            "bbox_handl2d": [469.85, 310.11, 522.95, 345.39, 0.57],
            "bbox_handr2d": [299.14, 445.18, 350.95, 486.70, 0.40],
            "keypoints": [
              [ 481.35,  324.78,    0.92], 
              [ 484.00,  369.43,    0.92], 
              [ 433.80,  386.26,    0.90], 
              [ 411.34,  456.21,    0.94], 
              [ 341.40,  461.70,    0.86], 
              [ 537.11,  358.26,    0.79], 
              [ 593.06,  330.27,    0.88], 
              [ 525.86,  324.76,    0.93], 
              [ 511.95,  545.59,    0.79], 
              [ 478.43,  548.30,    0.83], 
              [ 433.74,  657.32,    0.92], 
              [ 391.75,  732.83,    0.88], 
              [ 548.28,  545.50,    0.82], 
              [ 567.82,  657.39,    0.91], 
              [ 525.85,  749.50,    0.94], 
              [ 472.81,  313.58,    0.83], 
              [ 498.01,  310.80,    0.81], 
              [ 442.15,  302.44,    0.84], 
              [ 506.36,  302.38,    0.37], 
              [ 559.52,  788.63,    0.79], 
              [ 565.00,  774.69,    0.78], 
              [ 506.42,  752.40,    0.81], 
              [ 375.01,  769.24,    0.86], 
              [ 366.54,  760.74,    0.85], 
              [ 391.84,  741.23,    0.73]
            ],
            "handl2d": [
              [ 518.53,  332.56,    0.34], 
              [ 508.08,  339.43,    0.41], 
              [ 489.94,  342.45,    0.54], 
              [ 483.07,  336.96,    0.39], 
              [ 474.28,  335.58,    0.55], 
              [ 486.37,  318.54,    0.34], 
              [ 482.52,  328.16,    0.57], 
              [ 485.27,  332.83,    0.51], 
              [ 489.67,  333.93,    0.43], 
              [ 489.39,  316.62,    0.65], 
              [ 486.10,  327.06,    0.53], 
              [ 492.14,  330.91,    0.57], 
              [ 496.26,  331.73,    0.53], 
              [ 494.34,  313.60,    0.71], 
              [ 491.32,  322.39,    0.48], 
              [ 496.26,  327.61,    0.66], 
              [ 499.84,  328.16,    0.58], 
              [ 500.39,  313.05,    0.84], 
              [ 495.99,  319.64,    0.80], 
              [ 499.01,  324.04,    0.76], 
              [ 502.58,  324.31,    0.72]
            ],
            "handr2d": [
              [ 346.63,  483.24,    0.05], 
              [ 340.06,  471.23,    0.18], 
              [ 326.33,  464.65,    0.13], 
              [ 308.60,  448.64,    0.38], 
              [ 303.74,  452.93,    0.32], 
              [ 325.76,  459.79,    0.36], 
              [ 315.75,  448.64,    0.68], 
              [ 308.60,  450.64,    0.58], 
              [ 303.46,  454.93,    0.76], 
              [ 326.62,  464.94,    0.36], 
              [ 316.61,  457.22,    0.25], 
              [ 308.03,  459.22,    0.52], 
              [ 305.46,  460.08,    0.35], 
              [ 323.76,  470.94,    0.34], 
              [ 314.61,  466.08,    0.26], 
              [ 307.17,  465.51,    0.55], 
              [ 305.74,  465.51,    0.39], 
              [ 316.32,  475.23,    0.33], 
              [ 308.03,  473.52,    0.51], 
              [ 307.75,  471.52,    0.63], 
              [ 312.32,  471.23,    0.40]
            ],
            "isKeyframe": false
        }
    ],
    "isKeyframe": false
}

