{
    "filename": "images/06/000163.jpg",
    "height": 1024,
    "width": 1024,
    "annots": [
        {
            "personID": 0,
            "bbox": [386.72, 247.52, 715.50, 905.00, 0.76],
            "bbox_handl2d": [0.00, 0.00, 100.00, 100.00, 0.00],
            "bbox_handr2d": [682.75, 278.47, 727.28, 323.51, 0.55],
            "keypoints": [
              [ 587.47,  319.20,    0.91], 
              [ 525.93,  369.45,    0.76], 
              [ 520.34,  369.58,    0.84], 
              [ 615.54,  397.42,    0.82], 
              [ 688.10,  322.03,    0.85], 
              [ 539.92,  369.42,    0.65], 
              [ 615.35,  408.54,    0.13], 
              [   0.00,    0.00,    0.00], 
              [ 506.46,  548.35,    0.76], 
              [ 489.69,  548.41,    0.71], 
              [ 495.27,  699.20,    0.84], 
              [ 433.61,  813.97,    0.90], 
              [ 526.06,  548.26,    0.77], 
              [ 545.52,  654.60,    0.90], 
              [ 523.19,  749.62,    0.91], 
              [ 573.55,  302.46,    0.90], 
              [ 590.12,  302.34,    0.13], 
              [ 537.21,  302.31,    0.88], 
              [   0.00,    0.00,    0.00], 
              [ 565.11,  785.90,    0.81], 
              [ 567.79,  772.02,    0.81], 
              [ 503.76,  758.00,    0.80], 
              [ 481.32,  844.64,    0.81], 
              [ 461.72,  850.21,    0.79], 
              [ 414.12,  822.23,    0.90]
            ],
            "handl2d": [
              [   0.00,    0.00,    0.00], 
              [   0.00,    0.00,    0.00], 
              [   0.00,    0.00,    0.00], 
              [   0.00,    0.00,    0.00], 
              [   0.00,    0.00,    0.00], 
              [   0.00,    0.00,    0.00], 
              [   0.00,    0.00,    0.00], 
              [   0.00,    0.00,    0.00], 
              [   0.00,    0.00,    0.00], 
              [   0.00,    0.00,    0.00], 
              [   0.00,    0.00,    0.00], 
              [   0.00,    0.00,    0.00], 
              [   0.00,    0.00,    0.00], 
              [   0.00,    0.00,    0.00], 
              [   0.00,    0.00,    0.00], 
              [   0.00,    0.00,    0.00], 
              [   0.00,    0.00,    0.00], 
              [   0.00,    0.00,    0.00], 
              [   0.00,    0.00,    0.00], 
              [   0.00,    0.00,    0.00], 
              [   0.00,    0.00,    0.00]
            ],
            "handr2d": [
              [ 690.72,  319.75,    0.58], 
              [ 686.46,  308.66,    0.58], 
              [ 689.87,  292.46,    0.59], 
              [ 698.83,  285.63,    0.36], 
              [ 706.93,  285.63,    0.26], 
              [ 694.56,  289.90,    0.37], 
              [ 700.11,  282.22,    0.63], 
              [ 702.24,  285.20,    0.47], 
              [ 701.81,  290.32,    0.35], 
              [ 705.23,  295.87,    0.52], 
              [ 711.20,  285.20,    0.66], 
              [ 710.77,  290.75,    0.55], 
              [ 708.64,  295.44,    0.52], 
              [ 712.90,  303.12,    0.65], 
              [ 717.59,  292.46,    0.66], 
              [ 716.74,  298.00,    0.64], 
              [ 713.75,  302.26,    0.61], 
              [ 720.15,  309.52,    0.68], 
              [ 723.57,  302.69,    0.63], 
              [ 721.43,  304.82,    0.62], 
              [ 718.45,  307.38,    0.55]
            ],
            "isKeyframe": false
        }
    ],
    "isKeyframe": false
}

