{
    "filename": "images/04/000521.jpg",
    "height": 1024,
    "width": 1024,
    "annots": [
        {
            "personID": 0,
            "bbox": [293.48, 195.85, 669.09, 769.36, 0.86],
            "bbox_handl2d": [623.42, 415.07, 660.56, 440.34, 0.67],
            "bbox_handr2d": [288.28, 342.24, 340.33, 365.87, 0.37],
            "keypoints": [
              [ 484.06,  257.68,    0.91], 
              [ 506.49,  316.29,    0.86], 
              [ 458.84,  319.06,    0.89], 
              [ 394.58,  344.39,    0.90], 
              [ 324.78,  349.83,    0.86], 
              [ 565.04,  308.03,    0.83], 
              [ 629.40,  366.53,    0.87], 
              [ 637.78,  411.33,    0.90], 
              [ 528.86,  481.32,    0.81], 
              [ 500.73,  484.09,    0.81], 
              [ 484.07,  590.35,    0.91], 
              [ 484.05,  682.43,    0.91], 
              [ 567.97,  481.24,    0.83], 
              [ 593.02,  593.08,    0.93], 
              [ 620.99,  679.57,    0.84], 
              [ 478.40,  249.29,    0.90], 
              [ 500.69,  246.51,    0.88], 
              [   0.00,    0.00,    0.00], 
              [ 525.95,  243.64,    0.89], 
              [ 612.67,  721.57,    0.86], 
              [ 634.86,  713.23,    0.83], 
              [ 626.55,  679.73,    0.77], 
              [ 472.83,  710.53,    0.78], 
              [ 458.82,  704.84,    0.90], 
              [ 497.99,  685.38,    0.85]
            ],
            "handl2d": [
              [ 637.36,  417.18,    0.38], 
              [ 631.62,  419.73,    0.66], 
              [ 626.51,  425.15,    0.78], 
              [ 630.02,  431.86,    0.76], 
              [ 634.49,  438.24,    0.88], 
              [ 639.59,  417.82,    0.68], 
              [ 638.64,  430.58,    0.69], 
              [ 635.76,  434.41,    0.42], 
              [ 635.45,  434.41,    0.33], 
              [ 647.25,  419.41,    0.75], 
              [ 642.78,  434.73,    0.70], 
              [ 641.51,  436.64,    0.77], 
              [ 642.15,  433.13,    0.62], 
              [ 653.95,  422.28,    0.76], 
              [ 649.16,  437.28,    0.82], 
              [ 646.93,  437.60,    0.71], 
              [ 646.93,  435.05,    0.55], 
              [ 657.46,  426.75,    0.74], 
              [ 654.59,  437.28,    0.66], 
              [ 653.95,  437.28,    0.71], 
              [ 652.36,  436.64,    0.61]
            ],
            "handr2d": [
              [ 335.99,  352.20,    0.15], 
              [ 326.29,  351.06,    0.45], 
              [ 314.30,  353.06,    0.77], 
              [ 304.60,  358.19,    0.78], 
              [ 298.04,  363.90,    0.73], 
              [ 300.61,  345.35,    0.54], 
              [ 296.04,  354.48,    0.22], 
              [ 293.76,  359.62,    0.52], 
              [ 292.62,  363.90,    0.51], 
              [ 300.03,  344.78,    0.25], 
              [ 295.75,  350.77,    0.31], 
              [ 296.61,  357.05,    0.36], 
              [ 299.75,  361.90,    0.34], 
              [ 300.89,  344.21,    0.15], 
              [ 296.61,  352.20,    0.26], 
              [ 300.61,  357.34,    0.31], 
              [ 302.32,  359.62,    0.33], 
              [ 304.89,  348.20,    0.15], 
              [ 298.32,  352.48,    0.21], 
              [ 300.89,  357.91,    0.17], 
              [ 306.03,  358.19,    0.22]
            ],
            "isKeyframe": false
        }
    ],
    "isKeyframe": false
}

