{
    "filename": "images/17/000159.jpg",
    "height": 1024,
    "width": 1024,
    "annots": [
        {
            "personID": 0,
            "bbox": [186.39, 92.01, 505.04, 739.18, 0.79],
            "bbox_handl2d": [149.09, 306.37, 207.28, 341.79, 0.57],
            "bbox_handr2d": [197.91, 112.84, 232.27, 147.60, 0.15],
            "keypoints": [
              [ 299.54,  168.18,    0.52], 
              [ 366.59,  224.13,    0.80], 
              [ 369.53,  210.17,    0.74], 
              [ 282.79,  210.22,    0.92], 
              [ 232.39,  145.94,    0.89], 
              [ 363.91,  235.32,    0.82], 
              [ 316.37,  330.30,    0.83], 
              [ 212.95,  327.53,    0.86], 
              [ 405.79,  405.75,    0.70], 
              [ 419.80,  391.88,    0.65], 
              [ 411.40,  497.96,    0.84], 
              [ 461.71,  584.67,    0.80], 
              [ 389.10,  414.12,    0.74], 
              [ 363.78,  545.43,    0.84], 
              [ 389.01,  674.15,    0.87], 
              [   0.00,    0.00,    0.00], 
              [ 299.53,  159.80,    0.65], 
              [   0.00,    0.00,    0.00], 
              [ 319.08,  157.04,    0.86], 
              [ 344.39,  668.53,    0.79], 
              [ 352.65,  679.71,    0.82], 
              [ 400.19,  685.25,    0.76], 
              [ 422.51,  595.84,    0.82], 
              [ 430.87,  590.35,    0.78], 
              [ 478.49,  592.98,    0.78]
            ],
            "handl2d": [
              [ 202.44,  334.20,    0.44], 
              [ 194.00,  325.35,    0.36], 
              [ 177.56,  315.23,    0.29], 
              [ 167.01,  318.18,    0.25], 
              [ 153.94,  321.55,    0.17], 
              [ 181.35,  309.32,    0.71], 
              [ 166.17,  316.49,    0.67], 
              [ 159.84,  320.29,    0.76], 
              [ 153.94,  321.97,    0.75], 
              [ 184.30,  317.34,    0.63], 
              [ 167.86,  325.35,    0.63], 
              [ 167.01,  328.72,    0.55], 
              [ 170.39,  328.30,    0.46], 
              [ 187.68,  324.08,    0.66], 
              [ 171.23,  331.67,    0.64], 
              [ 170.39,  334.62,    0.64], 
              [ 172.07,  335.05,    0.50], 
              [ 188.52,  332.10,    0.79], 
              [ 177.56,  337.15,    0.63], 
              [ 175.03,  338.42,    0.74], 
              [ 174.60,  338.84,    0.66]
            ],
            "handr2d": [
              [ 216.76,  137.05,    0.01], 
              [ 227.75,  121.40,    0.03], 
              [ 218.42,  115.41,    0.04], 
              [ 214.76,  119.74,    0.05], 
              [ 213.43,  120.73,    0.02], 
              [ 229.41,  142.04,    0.06], 
              [ 226.75,  144.04,    0.11], 
              [ 216.43,  144.71,    0.08], 
              [ 209.10,  144.37,    0.05], 
              [ 228.41,  135.05,    0.07], 
              [ 221.75,  137.05,    0.20], 
              [ 211.10,  140.71,    0.16], 
              [ 204.77,  139.04,    0.14], 
              [ 223.42,  131.06,    0.07], 
              [ 217.76,  132.39,    0.13], 
              [ 206.77,  129.39,    0.12], 
              [ 200.78,  130.72,    0.27], 
              [ 222.42,  115.74,    0.08], 
              [ 211.10,  123.40,    0.17], 
              [ 205.44,  124.06,    0.35], 
              [ 201.11,  128.39,    0.30]
            ],
            "isKeyframe": false
        }
    ],
    "isKeyframe": false
}

