{
    "filename": "images/14/000008.jpg",
    "height": 1024,
    "width": 1024,
    "annots": [
        {
            "personID": 0,
            "bbox": [370.87, 121.79, 689.52, 779.24, 0.74],
            "bbox_handl2d": [0.00, 0.00, 100.00, 100.00, 0.00],
            "bbox_handr2d": [0.00, 0.00, 100.00, 100.00, 0.00],
            "keypoints": [
              [   0.00,    0.00,    0.00], 
              [ 545.60,  268.80,    0.90], 
              [ 604.26,  277.10,    0.82], 
              [ 662.96,  235.25,    0.87], 
              [ 615.45,  176.57,    0.82], 
              [ 484.06,  263.21,    0.82], 
              [ 402.95,  330.30,    0.78], 
              [ 433.79,  333.14,    0.15], 
              [ 500.74,  458.93,    0.77], 
              [ 531.63,  467.29,    0.68], 
              [ 545.54,  584.68,    0.85], 
              [ 562.24,  704.92,    0.81], 
              [ 458.93,  456.05,    0.74], 
              [ 414.23,  548.48,    0.86], 
              [ 433.65,  688.13,    0.82], 
              [   0.00,    0.00,    0.00], 
              [   0.00,    0.00,    0.00], 
              [ 590.22,  190.46,    0.67], 
              [ 526.11,  187.69,    0.91], 
              [ 397.43,  721.66,    0.59], 
              [ 400.19,  721.59,    0.68], 
              [ 442.12,  704.82,    0.79], 
              [ 534.33,  688.05,    0.62], 
              [ 545.44,  688.05,    0.56], 
              [ 565.08,  724.45,    0.79]
            ],
            "handl2d": [
              [ 408.45,  325.97,    0.07], 
              [ 421.58,  325.20,    0.01], 
              [ 422.74,  323.65,    0.01], 
              [ 453.63,  320.95,    0.00], 
              [ 455.56,  319.79,    0.00], 
              [ 452.85,  320.18,    0.00], 
              [ 454.78,  319.79,    0.00], 
              [ 459.42,  317.09,    0.00], 
              [ 456.71,  318.63,    0.00], 
              [ 407.29,  332.54,    0.00], 
              [ 461.74,  314.77,    0.00], 
              [ 461.35,  315.55,    0.00], 
              [ 470.23,  331.38,    0.00], 
              [ 408.45,  333.69,    0.00], 
              [ 469.07,  332.15,    0.00], 
              [ 448.61,  337.17,    0.00], 
              [ 448.22,  336.40,    0.00], 
              [ 411.15,  313.62,    0.00], 
              [ 462.89,  312.84,    0.00], 
              [ 470.62,  331.38,    0.00], 
              [ 470.23,  331.38,    0.00]
            ],
            "handr2d": [
              [ 608.39,  175.68,    0.02], 
              [ 606.23,  172.29,    0.01], 
              [ 603.46,  167.68,    0.01], 
              [ 603.77,  167.37,    0.01], 
              [ 603.46,  167.98,    0.00], 
              [ 608.69,  154.75,    0.02], 
              [ 605.00,  167.06,    0.01], 
              [ 600.69,  170.14,    0.01], 
              [ 588.38,  161.52,    0.01], 
              [ 602.54,  165.21,    0.01], 
              [ 600.69,  164.60,    0.01], 
              [ 597.92,  171.98,    0.01], 
              [ 597.62,  172.91,    0.01], 
              [ 600.69,  165.21,    0.01], 
              [ 598.85,  163.67,    0.01], 
              [ 597.92,  168.29,    0.01], 
              [ 596.38,  171.98,    0.01], 
              [ 617.93,  171.06,    0.01], 
              [ 613.00,  167.37,    0.01], 
              [ 590.23,  163.06,    0.01], 
              [ 589.92,  163.37,    0.01]
            ],
            "isKeyframe": false
        }
    ],
    "isKeyframe": false
}

