{
    "filename": "images/19/000340.jpg",
    "height": 1024,
    "width": 1024,
    "annots": [
        {
            "personID": 0,
            "bbox": [281.28, 161.38, 499.36, 778.58, 0.84],
            "bbox_handl2d": [459.48, 220.15, 498.32, 252.74, 0.36],
            "bbox_handr2d": [309.52, 483.88, 322.43, 524.54, 0.11],
            "keypoints": [
              [ 335.93,  235.34,    0.90], 
              [ 347.18,  288.36,    0.89], 
              [ 299.60,  313.54,    0.86], 
              [ 319.19,  400.18,    0.80], 
              [ 321.80,  478.40,    0.79], 
              [ 403.00,  260.49,    0.81], 
              [ 464.45,  254.95,    0.70], 
              [ 481.19,  246.48,    0.76], 
              [ 389.07,  475.61,    0.80], 
              [ 349.87,  478.46,    0.77], 
              [ 324.81,  604.21,    0.85], 
              [ 324.72,  679.78,    0.95], 
              [ 428.14,  467.26,    0.71], 
              [ 456.01,  593.08,    0.92], 
              [ 419.80,  688.10,    0.83], 
              [ 321.91,  229.58,    0.92], 
              [ 346.96,  218.58,    0.90], 
              [ 299.55,  221.36,    0.85], 
              [ 366.56,  212.82,    0.91], 
              [ 453.35,  727.15,    0.91], 
              [ 458.83,  718.88,    0.86], 
              [ 408.62,  696.52,    0.83], 
              [ 305.21,  718.80,    0.82], 
              [ 299.45,  704.91,    0.89], 
              [ 333.13,  682.58,    0.77]
            ],
            "handl2d": [
              [ 471.09,  230.34,    0.03], 
              [ 464.75,  237.35,    0.10], 
              [ 463.39,  240.07,    0.19], 
              [ 466.34,  246.86,    0.20], 
              [ 471.09,  250.03,    0.12], 
              [ 462.72,  231.47,    0.69], 
              [ 469.05,  242.33,    0.39], 
              [ 472.00,  246.63,    0.28], 
              [ 472.22,  244.60,    0.23], 
              [ 471.32,  226.49,    0.73], 
              [ 479.69,  242.11,    0.49], 
              [ 480.37,  243.01,    0.23], 
              [ 479.24,  240.75,    0.18], 
              [ 478.79,  224.22,    0.69], 
              [ 486.03,  236.90,    0.63], 
              [ 486.48,  239.16,    0.16], 
              [ 487.61,  236.22,    0.09], 
              [ 486.71,  222.87,    0.65], 
              [ 493.27,  230.34,    0.61], 
              [ 495.08,  233.96,    0.35], 
              [ 493.73,  238.94,    0.17]
            ],
            "handr2d": [
              [ 313.86,  479.12,    0.02], 
              [ 318.42,  479.12,    0.03], 
              [ 316.14,  487.92,    0.07], 
              [ 313.53,  501.28,    0.13], 
              [ 310.60,  511.38,    0.15], 
              [ 317.12,  487.26,    0.10], 
              [ 311.58,  509.75,    0.12], 
              [ 313.53,  516.26,    0.14], 
              [ 315.81,  521.15,    0.16], 
              [ 322.33,  489.87,    0.05], 
              [ 319.72,  507.14,    0.07], 
              [ 321.35,  515.29,    0.06], 
              [ 322.00,  519.52,    0.05], 
              [ 323.63,  488.24,    0.03], 
              [ 326.89,  510.07,    0.05], 
              [ 326.89,  512.68,    0.04], 
              [ 326.89,  514.31,    0.03], 
              [ 318.42,  485.63,    0.02], 
              [ 331.13,  512.68,    0.02], 
              [ 331.78,  513.01,    0.02], 
              [ 315.49,  521.15,    0.01]
            ],
            "isKeyframe": false
        }
    ],
    "isKeyframe": false
}

