{
    "filename": "images/15/000169.jpg",
    "height": 1024,
    "width": 1024,
    "annots": [
        {
            "personID": 0,
            "bbox": [238.39, 284.77, 503.32, 965.61, 0.79],
            "bbox_handl2d": [415.17, 616.56, 458.99, 653.25, 0.68],
            "bbox_handr2d": [235.96, 335.38, 280.61, 367.41, 0.48],
            "keypoints": [
              [ 366.50,  349.89,    0.89], 
              [ 405.79,  414.20,    0.87], 
              [ 363.89,  391.94,    0.85], 
              [ 293.93,  391.90,    0.81], 
              [ 260.47,  369.35,    0.86], 
              [ 442.09,  436.50,    0.83], 
              [ 481.25,  545.42,    0.93], 
              [ 456.02,  612.70,    0.90], 
              [ 408.63,  607.01,    0.76], 
              [ 388.95,  598.61,    0.76], 
              [ 366.74,  699.32,    0.90], 
              [ 430.92,  794.29,    0.82], 
              [ 430.86,  612.59,    0.75], 
              [ 391.86,  746.70,    0.88], 
              [ 436.49,  886.61,    0.86], 
              [ 366.62,  341.51,    0.15], 
              [ 372.24,  344.24,    0.91], 
              [   0.00,    0.00,    0.00], 
              [ 414.18,  347.22,    0.93], 
              [ 375.09,  903.20,    0.81], 
              [ 391.73,  908.87,    0.87], 
              [ 453.36,  903.38,    0.85], 
              [ 383.44,  816.79,    0.63], 
              [ 388.88,  816.59,    0.58], 
              [ 447.74,  799.85,    0.66]
            ],
            "handl2d": [
              [ 446.85,  619.62,    0.63], 
              [ 435.81,  621.32,    0.60], 
              [ 422.22,  628.96,    0.72], 
              [ 418.83,  639.15,    0.73], 
              [ 420.52,  647.64,    0.63], 
              [ 432.84,  623.02,    0.77], 
              [ 421.80,  629.81,    0.48], 
              [ 419.25,  640.00,    0.62], 
              [ 420.10,  646.37,    0.52], 
              [ 442.60,  626.84,    0.74], 
              [ 429.44,  642.97,    0.70], 
              [ 429.44,  645.10,    0.72], 
              [ 432.41,  642.55,    0.66], 
              [ 449.40,  632.78,    0.81], 
              [ 438.78,  647.64,    0.73], 
              [ 437.08,  648.92,    0.74], 
              [ 439.21,  645.95,    0.64], 
              [ 455.34,  639.58,    0.80], 
              [ 446.42,  649.77,    0.65], 
              [ 446.00,  650.19,    0.79], 
              [ 445.57,  650.19,    0.66]
            ],
            "handr2d": [
              [ 249.69,  344.20,    0.06], 
              [ 273.04,  358.06,    0.06], 
              [ 276.89,  350.88,    0.56], 
              [ 272.53,  350.62,    0.60], 
              [ 264.83,  356.78,    0.80], 
              [ 257.64,  338.05,    0.70], 
              [ 260.47,  342.15,    0.55], 
              [ 261.75,  346.00,    0.52], 
              [ 259.70,  348.06,    0.25], 
              [ 249.17,  342.15,    0.81], 
              [ 254.82,  353.19,    0.61], 
              [ 255.59,  356.52,    0.40], 
              [ 254.31,  356.52,    0.24], 
              [ 243.78,  348.57,    0.72], 
              [ 249.17,  359.09,    0.62], 
              [ 250.46,  360.89,    0.38], 
              [ 249.94,  359.60,    0.26], 
              [ 239.68,  355.50,    0.65], 
              [ 241.99,  363.20,    0.63], 
              [ 244.30,  364.74,    0.44], 
              [ 244.30,  363.45,    0.30]
            ],
            "isKeyframe": false
        }
    ],
    "isKeyframe": false
}

