{
    "filename": "images/08/000345.jpg",
    "height": 1024,
    "width": 1024,
    "annots": [
        {
            "personID": 0,
            "bbox": [476.76, 195.05, 798.76, 778.74, 0.78],
            "bbox_handl2d": [488.54, 268.16, 517.02, 292.81, 0.41],
            "bbox_handr2d": [763.90, 494.65, 793.33, 527.91, 0.10],
            "keypoints": [
              [   0.00,    0.00,    0.00], 
              [ 660.08,  324.61,    0.95], 
              [ 713.23,  341.53,    0.82], 
              [ 732.80,  436.42,    0.89], 
              [ 771.93,  500.72,    0.91], 
              [ 607.07,  305.28,    0.80], 
              [ 511.97,  321.93,    0.81], 
              [ 503.60,  293.96,    0.77], 
              [ 632.12,  498.00,    0.76], 
              [ 660.16,  500.71,    0.78], 
              [ 676.89,  592.99,    0.86], 
              [ 702.03,  704.76,    0.91], 
              [ 593.12,  495.27,    0.74], 
              [ 573.47,  604.28,    0.82], 
              [ 598.60,  721.58,    0.85], 
              [   0.00,    0.00,    0.00], 
              [   0.00,    0.00,    0.00], 
              [ 690.87,  251.96,    0.57], 
              [ 635.02,  243.69,    0.87], 
              [ 567.97,  704.97,    0.70], 
              [ 567.92,  721.54,    0.78], 
              [ 609.84,  730.10,    0.81], 
              [ 704.84,  710.46,    0.43], 
              [ 721.53,  716.01,    0.53], 
              [ 702.06,  721.61,    0.84]
            ],
            "handl2d": [
              [ 504.02,  290.76,    0.41], 
              [ 509.33,  290.76,    0.37], 
              [ 513.58,  288.63,    0.51], 
              [ 514.64,  286.51,    0.46], 
              [ 513.58,  286.51,    0.29], 
              [ 513.23,  272.34,    0.71], 
              [ 513.58,  272.34,    0.42], 
              [ 512.16,  275.88,    0.35], 
              [ 511.10,  279.78,    0.25], 
              [ 504.73,  270.21,    0.65], 
              [ 505.79,  271.63,    0.46], 
              [ 505.44,  278.01,    0.30], 
              [ 505.08,  283.32,    0.29], 
              [ 496.94,  271.63,    0.71], 
              [ 499.06,  273.40,    0.39], 
              [ 499.77,  280.49,    0.22], 
              [ 499.77,  283.67,    0.24], 
              [ 490.92,  274.82,    0.73], 
              [ 493.75,  275.17,    0.34], 
              [ 494.10,  279.78,    0.28], 
              [ 494.10,  282.26,    0.26]
            ],
            "handr2d": [
              [ 769.91,  497.42,    0.31], 
              [ 777.73,  500.97,    0.10], 
              [ 786.26,  514.83,    0.04], 
              [ 788.39,  514.48,    0.02], 
              [ 769.55,  507.01,    0.01], 
              [ 790.88,  514.48,    0.08], 
              [ 787.32,  513.77,    0.05], 
              [ 783.77,  511.63,    0.04], 
              [ 766.71,  512.35,    0.02], 
              [ 785.19,  519.45,    0.06], 
              [ 778.44,  517.68,    0.08], 
              [ 772.75,  516.25,    0.07], 
              [ 769.55,  514.83,    0.07], 
              [ 768.84,  511.63,    0.07], 
              [ 774.53,  520.16,    0.12], 
              [ 772.40,  519.10,    0.09], 
              [ 771.68,  518.39,    0.05], 
              [ 766.35,  514.83,    0.13], 
              [ 767.07,  520.52,    0.10], 
              [ 767.07,  523.01,    0.11], 
              [ 767.78,  525.14,    0.07]
            ],
            "isKeyframe": false
        }
    ],
    "isKeyframe": false
}

