{
    "filename": "images/13/000486.jpg",
    "height": 1024,
    "width": 1024,
    "annots": [
        {
            "personID": 0,
            "bbox": [318.28, 295.93, 663.84, 943.27, 0.80],
            "bbox_handl2d": [537.67, 648.70, 576.62, 704.91, 0.50],
            "bbox_handr2d": [302.99, 334.81, 344.46, 366.39, 0.52],
            "keypoints": [
              [ 414.08,  366.73,    0.66], 
              [ 500.82,  411.45,    0.91], 
              [ 520.41,  386.25,    0.83], 
              [ 414.27,  400.22,    0.83], 
              [ 347.08,  366.60,    0.92], 
              [ 481.37,  436.46,    0.83], 
              [ 545.47,  545.43,    0.88], 
              [ 551.11,  643.33,    0.83], 
              [ 528.83,  593.05,    0.67], 
              [ 565.11,  587.40,    0.69], 
              [ 584.64,  696.42,    0.79], 
              [ 629.41,  816.65,    0.81], 
              [ 503.74,  604.24,    0.69], 
              [ 456.05,  727.24,    0.88], 
              [ 455.94,  872.59,    0.82], 
              [   0.00,    0.00,    0.00], 
              [ 411.48,  355.49,    0.80], 
              [   0.00,    0.00,    0.00], 
              [ 433.83,  349.87,    0.95], 
              [ 414.08,  855.79,    0.80], 
              [ 414.12,  861.51,    0.84], 
              [ 458.92,  889.32,    0.78], 
              [ 598.68,  813.79,    0.69], 
              [ 609.87,  813.74,    0.61], 
              [ 635.04,  836.17,    0.80]
            ],
            "handl2d": [
              [ 552.04,  653.38,    0.53], 
              [ 543.70,  665.44,    0.58], 
              [ 540.91,  683.99,    0.46], 
              [ 547.41,  695.12,    0.37], 
              [ 551.58,  700.22,    0.39], 
              [ 543.70,  687.24,    0.75], 
              [ 550.65,  698.37,    0.42], 
              [ 552.04,  698.83,    0.30], 
              [ 552.51,  696.05,    0.23], 
              [ 553.44,  685.84,    0.65], 
              [ 559.00,  693.73,    0.51], 
              [ 562.25,  690.95,    0.47], 
              [ 561.32,  685.84,    0.47], 
              [ 562.25,  682.13,    0.54], 
              [ 566.42,  690.95,    0.61], 
              [ 567.35,  686.77,    0.60], 
              [ 565.96,  681.21,    0.48], 
              [ 569.67,  680.28,    0.54], 
              [ 573.38,  686.31,    0.57], 
              [ 573.38,  684.45,    0.60], 
              [ 571.99,  679.82,    0.43]
            ],
            "handr2d": [
              [ 341.01,  361.40,    0.52], 
              [ 339.05,  353.94,    0.55], 
              [ 331.98,  346.48,    0.57], 
              [ 321.77,  344.12,    0.70], 
              [ 313.13,  350.01,    0.69], 
              [ 320.19,  337.44,    0.56], 
              [ 309.20,  344.12,    0.41], 
              [ 313.13,  350.01,    0.37], 
              [ 317.05,  350.40,    0.46], 
              [ 316.66,  342.55,    0.35], 
              [ 307.24,  353.55,    0.57], 
              [ 313.91,  356.69,    0.55], 
              [ 319.41,  355.51,    0.47], 
              [ 313.52,  348.44,    0.34], 
              [ 306.45,  357.87,    0.64], 
              [ 313.91,  360.22,    0.53], 
              [ 319.41,  359.44,    0.52], 
              [ 312.34,  356.30,    0.27], 
              [ 307.63,  362.19,    0.60], 
              [ 312.73,  363.76,    0.60], 
              [ 317.05,  363.36,    0.62]
            ],
            "isKeyframe": false
        }
    ],
    "isKeyframe": false
}

