{
    "filename": "images/18/000154.jpg",
    "height": 1024,
    "width": 1024,
    "annots": [
        {
            "personID": 0,
            "bbox": [112.95, 137.98, 542.21, 768.57, 0.75],
            "bbox_handl2d": [107.80, 231.43, 145.97, 277.97, 0.16],
            "bbox_handr2d": [0.00, 0.00, 100.00, 100.00, 0.00],
            "keypoints": [
              [   0.00,    0.00,    0.00], 
              [ 369.49,  266.09,    0.85], 
              [ 403.04,  257.56,    0.84], 
              [ 344.28,  316.38,    0.11], 
              [   0.00,    0.00,    0.00], 
              [ 344.27,  277.28,    0.84], 
              [ 235.36,  324.68,    0.89], 
              [ 148.72,  277.14,    0.83], 
              [ 411.34,  439.35,    0.75], 
              [ 433.80,  433.68,    0.75], 
              [ 439.36,  528.77,    0.84], 
              [ 500.82,  632.08,    0.85], 
              [ 388.86,  453.30,    0.72], 
              [ 363.85,  576.28,    0.83], 
              [ 391.70,  702.08,    0.91], 
              [   0.00,    0.00,    0.00], 
              [   0.00,    0.00,    0.00], 
              [ 369.36,  190.53,    0.32], 
              [ 319.17,  198.93,    0.85], 
              [ 363.76,  699.20,    0.70], 
              [ 363.80,  704.79,    0.81], 
              [ 403.03,  716.02,    0.77], 
              [ 470.08,  637.78,    0.75], 
              [ 478.45,  635.06,    0.70], 
              [ 506.44,  637.78,    0.83]
            ],
            "handl2d": [
              [ 138.43,  270.17,    0.02], 
              [ 136.69,  267.99,    0.02], 
              [ 130.59,  246.21,    0.05], 
              [ 142.79,  274.09,    0.08], 
              [ 142.79,  275.40,    0.02], 
              [ 136.25,  247.51,    0.04], 
              [ 131.02,  245.77,    0.06], 
              [ 122.31,  255.79,    0.15], 
              [ 117.95,  259.28,    0.09], 
              [ 134.94,  246.64,    0.04], 
              [ 129.72,  249.25,    0.09], 
              [ 121.00,  255.35,    0.24], 
              [ 111.42,  260.15,    0.26], 
              [ 134.51,  245.77,    0.04], 
              [ 127.54,  244.90,    0.14], 
              [ 118.82,  250.13,    0.19], 
              [ 111.42,  259.28,    0.25], 
              [ 130.15,  235.31,    0.05], 
              [ 127.97,  241.41,    0.12], 
              [ 116.64,  245.33,    0.23], 
              [ 110.98,  245.77,    0.35]
            ],
            "handr2d": [
              [   0.00,    0.00,    0.00], 
              [   0.00,    0.00,    0.00], 
              [   0.00,    0.00,    0.00], 
              [   0.00,    0.00,    0.00], 
              [   0.00,    0.00,    0.00], 
              [   0.00,    0.00,    0.00], 
              [   0.00,    0.00,    0.00], 
              [   0.00,    0.00,    0.00], 
              [   0.00,    0.00,    0.00], 
              [   0.00,    0.00,    0.00], 
              [   0.00,    0.00,    0.00], 
              [   0.00,    0.00,    0.00], 
              [   0.00,    0.00,    0.00], 
              [   0.00,    0.00,    0.00], 
              [   0.00,    0.00,    0.00], 
              [   0.00,    0.00,    0.00], 
              [   0.00,    0.00,    0.00], 
              [   0.00,    0.00,    0.00], 
              [   0.00,    0.00,    0.00], 
              [   0.00,    0.00,    0.00], 
              [   0.00,    0.00,    0.00]
            ],
            "isKeyframe": false
        }
    ],
    "isKeyframe": false
}

